setup.py
TSPbyMetaheuristics/__init__.py
TSPbyMetaheuristics/antColony.py
TSPbyMetaheuristics/hillClimbing.py
TSPbyMetaheuristics/simulatedAnnealing.py
TSPbyMetaheuristics/travelingSalesman.py
TSPbyMetaheuristics.egg-info/PKG-INFO
TSPbyMetaheuristics.egg-info/SOURCES.txt
TSPbyMetaheuristics.egg-info/dependency_links.txt
TSPbyMetaheuristics.egg-info/not-zip-safe
TSPbyMetaheuristics.egg-info/top_level.txt